j25ng_lotto/__init__.py
j25ng_lotto/draw.py
j25ng_lotto-0.2.1.dist-info/METADATA
j25ng_lotto-0.2.1.dist-info/WHEEL
j25ng_lotto-0.2.1.dist-info/top_level.txt
j25ng_lotto-0.2.1.dist-info/RECORD
