Metadata-Version: 2.1
Name: j25ng_lotto
Version: 0.2.1
Summary: Default template for PDM package
Author-email: j25ng <jsan2861@gmail.com>
License: MIT
Requires-Python: >=3.9
